pygwml/__init__.py
pygwml/pygwml.py
pygwml-0.0.1.dist-info/METADATA
pygwml-0.0.1.dist-info/WHEEL
pygwml-0.0.1.dist-info/top_level.txt
pygwml-0.0.1.dist-info/RECORD
