Metadata-Version: 2.4
Name: pygwml
Version: 0.0.1
Summary: Geographically Weighted Machine Learning in Python
Author-email: "Moin Tariq, Muhammad Irfan Haider Khan" <sci.mointariq@gmail.com>
License-Expression: MIT
Project-URL: Homepage, https://github.com/moin-t/PyGWML
Classifier: Programming Language :: Python :: 3
Classifier: Operating System :: OS Independent
Requires-Python: >=3.9
Requires-Dist: pandas>=1.3.0
Requires-Dist: numpy>=1.21.0
Requires-Dist: xgboost>=1.7.0
Requires-Dist: scikit-learn>=1.0.0
Requires-Dist: libpysal>=4.6.0
Requires-Dist: esda>=2.4.3
